<DOMSymbolItem xmlns:xsi="http://www.w3.org/2001/XMLSchema-instance" xmlns="http://ns.adobe.com/xfl/2008/" name="Imports/IceMelt/TL_IceMelt__TEDExpt" itemID="5ba94061-000011de" linkageExportForAS="true" linkageClassName="TL_IceMelt__TEDExpt" lastModified="1537818845">
  <timeline>
    <DOMTimeline name="TL_IceMelt__TEDExpt">
      <layers>
        <DOMLayer name="Layer_2" color="#9933CC" current="true" isSelected="true">
          <frames>
            <DOMFrame index="0" keyMode="9728">
              <elements>
                <DOMRectangleObject objectWidth="1919.7" objectHeight="1200" x="0" y="0" lockFlag="true">
                  <matrix>
                    <Matrix a="1.00015258789063"/>
                  </matrix>
                  <fill>
                    <SolidColor color="#0000FF"/>
                  </fill>
                </DOMRectangleObject>
              </elements>
            </DOMFrame>
          </frames>
        </DOMLayer>
      </layers>
    </DOMTimeline>
  </timeline>
</DOMSymbolItem>